Nsc371/__init__.py
Nsc371/core.py
Nsc371/nsc512.py
nsc371-0.6.0.dist-info/licenses/LICENSE.txt
nsc371-0.6.0.dist-info/METADATA
nsc371-0.6.0.dist-info/WHEEL
nsc371-0.6.0.dist-info/entry_points.txt
nsc371-0.6.0.dist-info/top_level.txt
nsc371-0.6.0.dist-info/RECORD
